tileserver/__init__.py
tileserver/errors.py
tileserver/multistaticmap.py
tileserver/staticmap.py
tileserver/tileserver.py
stscpy-1.1.1.dist-info/METADATA
stscpy-1.1.1.dist-info/WHEEL
stscpy-1.1.1.dist-info/top_level.txt
stscpy-1.1.1.dist-info/RECORD
