Metadata-Version: 2.1
Name: stscpy
Version: 1.1.1
Summary: Basic wrapper for SwiftTileserverCache
Home-page: https://github.com/ccev/stscpy
Author: ccev
Author-email: UNKNOWN
License: UNKNOWN
Platform: UNKNOWN
Requires-Dist: Pillow
Requires-Dist: requests
